LICENSE
MANIFEST.in
README.rst
setup.py
test_settings.py
backupdb/__init__.py
backupdb/management/__init__.py
backupdb/management/commands/__init__.py
backupdb/management/commands/backupdb.py
backupdb/management/commands/restoredb.py
backupdb/tests/__init__.py
backupdb/tests/commands.py
backupdb/tests/files.py
backupdb/tests/log.py
backupdb/tests/processes.py
backupdb/tests/utils.py
backupdb/tests/app/models.py
backupdb/tests/app/urls.py
backupdb/utils/__init__.py
backupdb/utils/commands.py
backupdb/utils/exceptions.py
backupdb/utils/files.py
backupdb/utils/log.py
backupdb/utils/processes.py
backupdb/utils/settings.py
django_backupdb.egg-info/PKG-INFO
django_backupdb.egg-info/SOURCES.txt
django_backupdb.egg-info/dependency_links.txt
django_backupdb.egg-info/requires.txt
django_backupdb.egg-info/top_level.txt